fs_search/__init__.py
fs_search/core.py
fs_search/main.py
fs_search/utils.py
fs_search-0.1.2.dist-info/LICENCE
fs_search-0.1.2.dist-info/METADATA
fs_search-0.1.2.dist-info/WHEEL
fs_search-0.1.2.dist-info/entry_points.txt
fs_search-0.1.2.dist-info/top_level.txt
fs_search-0.1.2.dist-info/RECORD
