Metadata-Version: 2.1
Name: fs-search
Version: 0.1.2
Summary: CLI tool for listing paths in the base directory
Home-page: https://github.com/voyager-2021/fs-search
Author: voyager-2021
Author-email: voyager-2019@outlook.com
License: MIT
Project-URL: Source, https://github.com/voyager-2021/fs-search
Project-URL: Issues, https://github.com/voyager-2021/fs-search/issues
Classifier: Programming Language :: Python :: 3
Classifier: Programming Language :: Python :: 3.10
Classifier: Programming Language :: Python :: 3.11
Classifier: Programming Language :: Python :: 3.12
Classifier: Programming Language :: Python :: 3.13
Classifier: License :: OSI Approved :: MIT License
Classifier: Operating System :: OS Independent
Requires-Python: <4.0,>=3.10
License-File: LICENCE
Requires-Dist: colorama>=0.4.6
Provides-Extra: dev
Requires-Dist: mypy>=1.13.0; extra == "dev"
Requires-Dist: setuptools>=75.6.0; extra == "dev"
Requires-Dist: twine>=6.0.1; extra == "dev"
Requires-Dist: build>=1.2.2.post1; extra == "dev"
Requires-Dist: wheel>=0.45.1; extra == "dev"
